{
  "body_length_m": 0.65,
  "body_width_m": 0.55,
  "body_height_m": 0.19,
  "body_clearance_m": 0.1,
  "wheel_radius_m": 0.095,
  "gimbal_length_m": 0.34,
  "gimbal_width_m": 0.2,
  "gimbal_body_height_m": 0.14,
  "gimbal_mount_gap_m": 0.1,
  "gimbal_mount_length_m": 0.12,
  "gimbal_mount_width_m": 0.13,
  "gimbal_mount_height_m": 0.06,
  "barrel_length_m": 0.1,
  "barrel_radius_m": 0.026,
  "gimbal_height_m": 0.52,
  "gimbal_offset_x_m": 0.0,
  "gimbal_offset_y_m": 0.0,
  "armor_plate_width_m": 0.01,
  "armor_plate_length_m": 0.2,
  "armor_plate_height_m": 0.13,
  "armor_plate_gap_m": 0.023,
  "armor_light_length_m": 0.023,
  "armor_light_width_m": 0.005,
  "armor_light_height_m": 0.095,
  "barrel_light_length_m": 0.1,
  "barrel_light_width_m": 0.02,
  "barrel_light_height_m": 0.05,
  "body_render_width_scale": 0.82,
  "wheel_style": "mecanum",
  "suspension_style": "four_bar",
  "arm_style": "none",
  "front_climb_assist_style": "belt_lift",
  "rear_climb_assist_style": "balance_leg",
  "role_key": "hero",
  "body_color_rgb": [
    166,
    174,
    186
  ],
  "turret_color_rgb": [
    232,
    232,
    236
  ],
  "armor_color_rgb": [
    224,
    229,
    234
  ],
  "wheel_color_rgb": [
    44,
    44,
    44
  ],
  "front_climb_assist_top_length_m": 0.065,
  "front_climb_assist_bottom_length_m": 0.03,
  "front_climb_assist_plate_width_m": 0.018,
  "front_climb_assist_plate_height_m": 0.18,
  "front_climb_assist_forward_offset_m": 0.0,
  "front_climb_assist_inner_offset_m": 0.0,
  "rear_climb_assist_upper_length_m": 0.22,
  "rear_climb_assist_lower_length_m": 0.25,
  "rear_climb_assist_upper_width_m": 0.03,
  "rear_climb_assist_upper_height_m": 0.032,
  "rear_climb_assist_lower_width_m": 0.028,
  "rear_climb_assist_lower_height_m": 0.03,
  "rear_climb_assist_mount_offset_x_m": 0.09,
  "rear_climb_assist_mount_height_m": 0.25,
  "rear_climb_assist_inner_offset_m": 0.0,
  "rear_climb_assist_upper_pair_gap_m": 0.044,
  "rear_climb_assist_hinge_radius_m": 0.016,
  "rear_climb_assist_knee_min_deg": 42.0,
  "rear_climb_assist_knee_max_deg": 132.0,
  "custom_wheel_positions_m": [
    [
      -0.254,
      -0.278
    ],
    [
      0.254,
      -0.278
    ],
    [
      -0.254,
      0.278
    ],
    [
      0.254,
      0.278
    ]
  ],
  "rear_climb_assist_knee_direction": "front"
}